Metadata-Version: 1.1
Name: thecalcLIB
Version: 0.0.1
Summary: This is a calculator package
Home-page: UNKNOWN
Author: Freddy Frolov
Author-email: freddyfrolov383@gmail.com
License: UNKNOWN
Keywords: calculator
Platform: UNKNOWN
Classifier: Development Status :: 5 - Production/Stable
Classifier: Intended Audience :: Education
Classifier: Operating System :: Microsoft :: Windows :: Windows 10
Classifier: License :: OSI Approved :: MIT License
Classifier: Programming Language :: Python :: 3
